ov_wag/__init__.py
ov_wag/_version.py
ov_wag/api.py
ov_wag/health.py
ov_wag/serializers.py
ov_wag/settings/__init__.py
ov_wag/settings/base.py
ov_wag/settings/dev.py
ov_wag/settings/production.py
ov_wag/settings/test.py
ov_wag/static/css/ov-wag.css
ov_wag/static/js/ov-wag.js
ov_wag/templates/404.html
ov_wag/templates/500.html
ov_wag/templates/base.html
ov_wag/templates/socialaccount/authentication_error.html
ov_wag/templates/wagtailadmin/login.html
ov_wag/templatetags/__init__.py
ov_wag/templatetags/custom_tags.py
ov_wag/tests/__init__.py
ov_wag/tests/test_api.py
ov_wag/tests/test_env.py
ov_wag/tests/test_health.py
ov_wag/urls.py
ov_wag/utils.py
ov_wag/wagtail_hooks.py
ov_wag/wsgi.py
ov_wag-1.1.2.dist-info/WHEEL
ov_wag-1.1.2.dist-info/entry_points.txt
ov_wag-1.1.2.dist-info/METADATA
ov_wag-1.1.2.dist-info/RECORD
